AMS_BP/__init__.py
AMS_BP/main_cli.py
AMS_BP/core/__init__.py
AMS_BP/core/run_sim_util.py
AMS_BP/core/sim_microscopy.py
AMS_BP/core/cells/__init__.py
AMS_BP/core/cells/budding_yeast_cell.py
AMS_BP/core/cells/cell_factory.py
AMS_BP/core/configio/__init__.py
AMS_BP/core/configio/configmodels.py
AMS_BP/core/configio/convertconfig.py
AMS_BP/core/configio/experiments.py
AMS_BP/core/configio/saving.py
AMS_BP/core/groundtruth_generators/__init__.py
AMS_BP/core/groundtruth_generators/nuclearporecomplexes.py
AMS_BP/core/metadata/__init__.py
AMS_BP/core/metadata/metadata.py
AMS_BP/core/motion/__init__.py
AMS_BP/core/motion/condensate_movement.py
AMS_BP/core/motion/track_gen.py
AMS_BP/core/motion/movement/__init__.py
AMS_BP/core/motion/movement/boundary_conditions.py
AMS_BP/core/optics/__init__.py
AMS_BP/core/optics/collection_efficiency.py
AMS_BP/core/optics/camera/__init__.py
AMS_BP/core/optics/camera/detectors.py
AMS_BP/core/optics/camera/quantum_eff.py
AMS_BP/core/optics/filters/__init__.py
AMS_BP/core/optics/filters/filters.py
AMS_BP/core/optics/filters/channels/__init__.py
AMS_BP/core/optics/filters/channels/channelschema.py
AMS_BP/core/optics/lasers/__init__.py
AMS_BP/core/optics/lasers/laser_profiles.py
AMS_BP/core/optics/lasers/scanning_patterns.py
AMS_BP/core/optics/psf/__init__.py
AMS_BP/core/optics/psf/psf_engine.py
AMS_BP/core/photophysics/__init__.py
AMS_BP/core/photophysics/photon_physics.py
AMS_BP/core/photophysics/state_kinetics.py
AMS_BP/core/probabilityfuncs/__init__.py
AMS_BP/core/probabilityfuncs/markov_chain.py
AMS_BP/core/probabilityfuncs/probability_functions.py
AMS_BP/core/sample/__init__.py
AMS_BP/core/sample/sim_sampleplane.py
AMS_BP/core/sample/flurophores/__init__.py
AMS_BP/core/sample/flurophores/flurophore_schema.py
AMS_BP/gui/README.md
AMS_BP/gui/__init__.py
AMS_BP/gui/main.py
AMS_BP/gui/sim_worker.py
AMS_BP/gui/assets/__init__.py
AMS_BP/gui/assets/drawing.svg
AMS_BP/gui/help_docs/__init__.py
AMS_BP/gui/help_docs/cell_help.md
ams_bp-0.4.42.dist-info/METADATA
ams_bp-0.4.42.dist-info/WHEEL
ams_bp-0.4.42.dist-info/entry_points.txt
ams_bp-0.4.42.dist-info/licenses/LICENSE
ams_bp-0.4.42.dist-info/RECORD
