Metadata-Version: 2.4
Name: AMS_BP
Version: 0.4.42
Summary: Advanced Microscopy Simulations developed for the Weber Lab by Baljyot Singh Parmar
Project-URL: Documentation, https://joemans3.github.io/AMS_BP/
Project-URL: Source code, https://github.com/joemans3/AMS_BP
Author-email: Baljyot Singh Parmar <baljyotparmar@hotmail.com>
Maintainer-email: Baljyot Singh Parmar <baljyotparmar@hotmail.com>
License-File: LICENSE
Keywords: SMS
Requires-Python: >=3.12
Requires-Dist: boundedfbm>=0.4.0
Requires-Dist: jsonschema>=4.23.0
Requires-Dist: napari[all]>=0.5.6
Requires-Dist: numpy>=1.21.2
Requires-Dist: pydantic>=2.9.2
Requires-Dist: pyqt6>=6.9.0
Requires-Dist: pyvista>=0.44.2
Requires-Dist: scikit-image>=0.18.3
Requires-Dist: scipy>=1.7.1
Requires-Dist: tifffile>=2024.12.12
Requires-Dist: tomli>=2.0.2
Requires-Dist: tomlkit>=0.13.2
Requires-Dist: typer>=0.12.5
